catsmoothing-0.3.1.dist-info/METADATA
catsmoothing-0.3.1.dist-info/WHEEL
catsmoothing-0.3.1.dist-info/licenses/LICENSE
catsmoothing-0.3.1.dist-info/licenses/AUTHORS.md
catsmoothing/api.py
catsmoothing/tests/test_catsmoothing.py
catsmoothing/__init__.py
catsmoothing/_catsmoothing.pyi
catsmoothing/_catsmoothing.cpython-310-s390x-linux-gnu.so
catsmoothing-0.3.1.dist-info/RECORD
