Metadata-Version: 2.4
Name: catsmoothing
Version: 0.3.1
Classifier: Development Status :: 4 - Beta
Classifier: Intended Audience :: Science/Research
Classifier: License :: OSI Approved :: MIT License
Classifier: Operating System :: OS Independent
Classifier: Programming Language :: Python
Classifier: Programming Language :: Python :: 3 :: Only
Classifier: Programming Language :: Python :: 3.10
Classifier: Programming Language :: Python :: 3.11
Classifier: Programming Language :: Python :: 3.12
Classifier: Programming Language :: Python :: 3.13
Classifier: Programming Language :: Rust
Classifier: Topic :: Scientific/Engineering
Classifier: Topic :: Scientific/Engineering :: GIS
Classifier: Typing :: Typed
Requires-Dist: numpy>=2
Requires-Dist: shapely>=2
Requires-Dist: pytest-codspeed ; extra == 'benchmark'
Requires-Dist: ipykernel ; extra == 'dev'
Requires-Dist: ipywidgets ; extra == 'dev'
Requires-Dist: matplotlib ; extra == 'dev'
Requires-Dist: pytest ; extra == 'dev'
Requires-Dist: black ; extra == 'docs'
Requires-Dist: mkdocs ; extra == 'docs'
Requires-Dist: mkdocs-jupyter ; extra == 'docs'
Requires-Dist: mkdocs-material ; extra == 'docs'
Requires-Dist: mkdocstrings-python ; extra == 'docs'
Requires-Dist: codespell ; extra == 'lint'
Requires-Dist: pre-commit ; extra == 'lint'
Requires-Dist: coverage[toml] ; extra == 'test'
Requires-Dist: pytest-cov ; extra == 'test'
Requires-Dist: pytest-sugar ; extra == 'test'
Requires-Dist: pyright ; extra == 'typecheck'
Provides-Extra: benchmark
Provides-Extra: dev
Provides-Extra: docs
Provides-Extra: lint
Provides-Extra: test
Provides-Extra: typecheck
License-File: LICENSE
License-File: AUTHORS.md
Summary: Smoothing Shapely geometries using Catmull-Rom spline
Home-Page: https://github.com/cheginit/catsmoothing
Author: Taher Chegini <cheginit@gmail.com>
Author-email: Taher Chegini <cheginit@gmail.com>
License: MIT
Requires-Python: >=3.10
Project-URL: Changelog, https://github.com/cheginit/catsmoothing/blob/main/CHANGELOG.md
Project-URL: CI, https://github.com/cheginit/catsmoothing/actions
Project-URL: Homepage, https://github.com/cheginit/catsmoothing
Project-URL: Issues, https://github.com/cheginit/catsmoothing/issues
